hacha/__init__.py
hacha/hacha.py
hacha-0.1.0.dist-info/licenses/LICENSE
hacha-0.1.0.dist-info/WHEEL
hacha-0.1.0.dist-info/entry_points.txt
hacha-0.1.0.dist-info/METADATA
hacha-0.1.0.dist-info/RECORD
